[
  {
    "name": "Peggle™ Blast",
    "link": "http://www.ea.com/peggle-blast",
    "thumbnail_link": "http://web-vassets.ea.com/Assets/Resources/Image/FeaturedGame/PEGGLE_BLAST_thumbnail_298x168.jpg?cb=1416966602",
    "logo_link": "http://web-vassets.ea.com/Assets/Resources/Image/FullImageLogo/PEGGLE_BLAST_logo_170x100.png?cb=1416966603",
    "release_date": "To Be Announced",
    "additional_links": [

    ],
    "franchise": null,
    "platform": "pc",
    "genre": "action"
  },
  {
    "name": "Star Wars™ Battlefront™",
    "link": "http://www.ea.com/star-wars-battlefront",
    "thumbnail_link": "http://web-vassets.ea.com/Assets/Resources/Image/FeaturedGame/SWBattlefront_298x168_v1.jpg?cb=1412974033",
    "logo_link": "http://web-vassets.ea.com/Assets/Resources/Image/FullImageLogo/SWBattlefront_gpd_logo_v1a.png?cb=1412974033",
    "release_date": "To Be Announced",
    "additional_links": [

    ],
    "franchise": null,
    "platform": "pc",
    "genre": "action"
  },
  {
    "name": "Mirror's Edge",
    "link": "http://www.ea.com/mirrors-edge",
    "thumbnail_link": "http://web-vassets.ea.com/Assets/Resources/Image/FeaturedGame/MirrorsEdge2_298x168.jpg?cb=1412974264",
    "logo_link": "http://web-vassets.ea.com/Assets/Resources/Image/FullImageLogo/MirrorsEdge2_gpd_logo.png?cb=1412974264",
    "release_date": "To Be Announced",
    "additional_links": [

    ],
    "franchise": null,
    "platform": "pc",
    "genre": "action"
  },
  {
    "name": "SimCity™ BuildIt",
    "link": "http://www.ea.com/simcity-buildit",
    "thumbnail_link": "http://web-vassets.ea.com/Assets/Resources/Image/FeaturedGame/SCTY_simcity_thumbnail_298x168_vb.png?cb=1412974030",
    "logo_link": "http://web-vassets.ea.com/Assets/Resources/Image/FullImageLogo/SCTY_simcity_logo.png?cb=1412974030",
    "release_date": null,
    "additional_links": [
      {
        "name": "View More SimCity Games",
        "link": "/simcity"
      }
    ],
    "franchise": "/simcity",
    "platform": "pc",
    "genre": "action"
  },
  {
    "name": "FIFA 15 Ultimate Team™ by EA SPORTS for iPad and iPhone",
    "link": "http://www.ea.com/fifa15ut-ios",
    "thumbnail_link": "http://web-vassets.ea.com/Assets/Resources/Image/FeaturedGame/fifa15-thumb-ios.png?cb=1412974027",
    "logo_link": "http://web-vassets.ea.com/Assets/Resources/Image/FullImageLogo/fifa15-logo-ios.png?cb=1412974027",
    "release_date": null,
    "additional_links": [
      {
        "name": "View More FIFA Games",
        "link": "/fifa"
      }
    ],
    "franchise": "/fifa",
    "platform": "pc",
    "genre": "shooting"
  },
  {
    "name": "FIFA 15 Ultimate Team™ by EA SPORTS for Android",
    "link": "http://www.ea.com/fifa15ut-and",
    "thumbnail_link": "http://web-vassets.ea.com/Assets/Resources/Image/FeaturedGame/fifa15-thumb-and.png?cb=1412974027",
    "logo_link": "http://web-vassets.ea.com/Assets/Resources/Image/FullImageLogo/fifa15-logo-ios.png?cb=1412974027",
    "release_date": null,
    "additional_links": [
      {
        "name": "View More FIFA Games",
        "link": "/fifa"
      }
    ],
    "franchise": "/fifa",
    "platform": "pc",
    "genre": "action"
  },
  {
    "name": "The Sims 4",
    "link": "http://www.ea.com/the-sims-4",
    "thumbnail_link": "http://web-vassets.ea.com/Assets/Resources/Image/FeaturedGame/TS4_banner_298x168.png?cb=1412974033",
    "logo_link": "http://web-vassets.ea.com/Assets/Resources/Image/FullImageLogo/TheSims4_GDP_logo_v1.png?cb=1412974033",
    "release_date": null,
    "additional_links": [
      {
        "name": "View More Sims Games",
        "link": "/sims"
      }
    ],
    "franchise": "/sims",
    "platform": "pc",
    "genre": "horror"
  },
  {
    "name": "MADDEN NFL Mobile for Android",
    "link": "http://www.ea.com/madnfl15-and",
    "thumbnail_link": "http://web-vassets.ea.com/Assets/Resources/Image/FeaturedGame/madden15-thumb-and.png?cb=1412974032",
    "logo_link": "http://web-vassets.ea.com/Assets/Resources/Image/FullImageLogo/madden15-logo-and.png?cb=1412974032",
    "release_date": null,
    "additional_links": [
      {
        "name": "View More Madden Games",
        "link": "/madden"
      }
    ],
    "franchise": "/madden",
    "platform": "pc",
    "genre": "action"
  },
  {
    "name": "MADDEN NFL Mobile for iPad and iPhone ",
    "link": "http://www.ea.com/madnfl15-ios",
    "thumbnail_link": "http://web-vassets.ea.com/Assets/Resources/Image/FeaturedGame/madden15-thumb-ios.png?cb=1412974032",
    "logo_link": "http://web-vassets.ea.com/Assets/Resources/Image/FullImageLogo/madden15-logo-ios.png?cb=1412974032",
    "release_date": null,
    "additional_links": [
      {
        "name": "View More Madden Games",
        "link": "/madden"
      }
    ],
    "franchise": "/madden",
    "platform": "mobile",
    "genre": "action"
  },
  {
    "name": "The Simpsons™: Tapped Out on Google Play",
    "link": "http://www.ea.com/simpsons-tapped-out-android",
    "thumbnail_link": "http://web-vassets.ea.com/Assets/Resources/Image/FeaturedGame/simpsons-tapped-out-refresh-thumb.png?cb=1412974369",
    "logo_link": "http://web-vassets.ea.com/Assets/Richmedia/Image/FullImageLogo/Simpsons_tapped-out_logo_EN_R5.png?cb=1412974369",
    "release_date": null,
    "additional_links": [

    ],
    "franchise": null,
    "platform": "mobile",
    "genre": "shooting"
  },
  {
    "name": "The Simpsons: Tapped Out for Kindle Fire",
    "link": "http://www.ea.com/simpsons-tapped-out-kindle",
    "thumbnail_link": "http://web-vassets.ea.com/Assets/Resources/Image/FeaturedGame/simpsons-tapped-out-refresh-thumb-kindf.png?cb=1412974259",
    "logo_link": "http://web-vassets.ea.com/Assets/Resources/Image/FullImageLogo/simpsons_tapped-out-refresh-logo-kindf.png?cb=1412974259",
    "release_date": null,
    "additional_links": [

    ],
    "franchise": null,
    "platform": "pc",
    "genre": "action"
  },
  {
    "name": "The Simpsons: Tapped Out for iPad and iPhone",
    "link": "http://www.ea.com/simpsons-tapped-out-ios",
    "thumbnail_link": "http://web-vassets.ea.com/Assets/Richmedia/Image/FeaturedGame/the-simpsons-tapped-out-ios-thumb.png?cb=1412974417",
    "logo_link": "http://web-vassets.ea.com/Assets/Richmedia/Image/FullImageLogo/Simpsons_tapped-out_logo_EN_R5.png?cb=1412974369",
    "release_date": null,
    "additional_links": [

    ],
    "franchise": null,
    "platform": "mobile",
    "genre": "shooting"
  },
  {
    "name": "The Sims™ FreePlay for Kindle Fire",
    "link": "http://www.ea.com/the-sims-freeplay-kindle-fire",
    "thumbnail_link": "http://web-vassets.ea.com/Assets/Resources/Image/FeaturedGame/sims-evergreen-thumb-ios.png?cb=1412974295",
    "logo_link": "http://web-vassets.ea.com/Assets/Resources/Image/FullImageLogo/sims-evergreen-logo3.png?cb=1412974295",
    "release_date": null,
    "additional_links": [
      {
        "name": "View More Sims Games",
        "link": "/sims"
      }
    ],
    "franchise": "/sims",
    "platform": "mobile",
    "genre": "action"
  },
  {
    "name": "The Sims™ FreePlay for iPad and iPhone",
    "link": "http://www.ea.com/the-sims-freeplay-ios",
    "thumbnail_link": "http://web-vassets.ea.com/Assets/Resources/Image/FeaturedGame/sims-evergreen-thumb-ios.png?cb=1412974295",
    "logo_link": "http://web-vassets.ea.com/Assets/Resources/Image/FullImageLogo/sims-evergreen-logo3.png?cb=1412974295",
    "release_date": null,
    "additional_links": [
      {
        "name": "View More Sims Games",
        "link": "/sims"
      }
    ],
    "franchise": "/sims",
    "platform": "pc",
    "genre": "action"
  },
  {
    "name": "The Sims™ FreePlay for Android",
    "link": "http://www.ea.com/the-sims-freeplay-android",
    "thumbnail_link": "http://web-vassets.ea.com/Assets/Resources/Image/FeaturedGame/sims-evergreen-thumb-ios.png?cb=1412974295",
    "logo_link": "http://web-vassets.ea.com/Assets/Resources/Image/FullImageLogo/sims-evergreen-logo3.png?cb=1412974295",
    "release_date": null,
    "additional_links": [
      {
        "name": "View More Sims Games",
        "link": "/sims"
      }
    ],
    "franchise": "/sims",
    "platform": "xbox",
    "genre": "action"
  },
  {
    "name": "Bejeweled Blitz",
    "link": "http://www.ea.com/bejeweled-blitz-ios",
    "thumbnail_link": "http://web-vassets.ea.com/Assets/Richmedia/Image/FeaturedGame/BejeweledBlitz-thumb-298x168.jpg?cb=1412974609",
    "logo_link": "http://web-vassets.ea.com/Assets/Richmedia/Image/FullImageLogo/BejeweledBlitz-logo-455x100.png?cb=1412974609",
    "release_date": null,
    "additional_links": [

    ],
    "franchise": null,
    "platform": "mobile",
    "genre": "action"
  },
  {
    "name": "Real Racing 3 for Kindle Fire",
    "link": "http://www.ea.com/real-racing-3-kf",
    "thumbnail_link": "http://web-vassets.ea.com/Assets/Resources/Image/FeaturedGame/real-racing-3-kf-thumb.png?cb=1412974354",
    "logo_link": "http://web-vassets.ea.com/Assets/Resources/Image/FullImageLogo/real-racing-3-ios-logo-r3.png?cb=1412974356",
    "release_date": null,
    "additional_links": [

    ],
    "franchise": null,
    "platform": "pc",
    "genre": "shooting"
  },
  {
    "name": "Real Racing 3 for iPad and iPhone",
    "link": "http://www.ea.com/real-racing-3-ios",
    "thumbnail_link": "http://web-vassets.ea.com/Assets/Resources/Image/FeaturedGame/real-racing-3-ios-thumb.png?cb=1412974356",
    "logo_link": "http://web-vassets.ea.com/Assets/Resources/Image/FullImageLogo/real-racing-3-ios-logo-r2.png?cb=1412974356",
    "release_date": null,
    "additional_links": [

    ],
    "franchise": null,
    "platform": "pc",
    "genre": "action"
  },
  {
    "name": "Real Racing 3 for Android",
    "link": "http://www.ea.com/real-racing-3-and",
    "thumbnail_link": "http://web-vassets.ea.com/Assets/Resources/Image/FeaturedGame/real-racing-3-and-thumb.png?cb=1412974354",
    "logo_link": "http://web-vassets.ea.com/Assets/Resources/Image/FullImageLogo/real-racing-3-ios-logo-r3.png?cb=1412974356",
    "release_date": null,
    "additional_links": [

    ],
    "franchise": null,
    "platform": "mobile",
    "genre": "shooting"
  },
  {
    "name": "Plants vs. Zombies 2",
    "link": "http://www.ea.com/plants-vs-zombies-2",
    "thumbnail_link": "http://web-vassets.ea.com/Assets/Resources/Image/FeaturedGame/GamesPg_thumb_298x168.jpg?cb=1421242202",
    "logo_link": "http://web-vassets.ea.com/Assets/Resources/Image/FullImageLogo/GDP_logo_100.png?cb=1421242202",
    "release_date": null,
    "additional_links": [

    ],
    "franchise": null,
    "platform": "pc",
    "genre": "action"
  },
  {
    "name": "Heroes of Dragon Age for Android",
    "link": "http://www.ea.com/hoda-and",
    "thumbnail_link": "http://web-vassets.ea.com/Assets/Resources/Image/FeaturedGame/heroes-of-dragon-age-thumb-and.png?cb=1412974153",
    "logo_link": "http://web-vassets.ea.com/Assets/Resources/Image/FullImageLogo/heroes-of-dragon-age-logo-and.png?cb=1412974153",
    "release_date": null,
    "additional_links": [
      {
        "name": "View More Dragon Age Games",
        "link": "/dragon-age"
      }
    ],
    "franchise": "/dragon-age",
    "platform": "pc",
    "genre": "action"
  },
  {
    "name": "Heroes of Dragon Age for iPad and iPhone",
    "link": "http://www.ea.com/hoda-ios",
    "thumbnail_link": "http://web-vassets.ea.com/Assets/Resources/Image/FeaturedGame/heroes-of-dragon-age-thumb-ios.png?cb=1412974153",
    "logo_link": "http://web-vassets.ea.com/Assets/Resources/Image/FullImageLogo/heroes-of-dragon-age-logo-ios.png?cb=1412974153",
    "release_date": null,
    "additional_links": [
      {
        "name": "View More Dragon Age Games",
        "link": "/dragon-age"
      }
    ],
    "franchise": "/dragon-age",
    "platform": "mobile",
    "genre": "action"
  },
  {
    "name": "Tetris® Blitz for iPad and iPhone",
    "link": "http://www.ea.com/tetris-blitz-ios",
    "thumbnail_link": "http://web-vassets.ea.com/Assets/Resources/Image/FeaturedGame/tetris-blitz-thumb.png?cb=1412974321",
    "logo_link": "http://web-vassets.ea.com/Assets/Resources/Image/FullImageLogo/tetris-blitz-logo-center-left_asset.png?cb=1412974321",
    "release_date": null,
    "additional_links": [

    ],
    "franchise": null,
    "platform": "xbox",
    "genre": "shooting"
  },
  {
    "name": "Tetris® Blitz for Kindle Fire",
    "link": "http://www.ea.com/tetris-blitz-kindle",
    "thumbnail_link": "http://web-vassets.ea.com/Assets/Resources/Image/FeaturedGame/tetris-blitz-thumb-kindf.png?cb=1412974301",
    "logo_link": "http://web-vassets.ea.com/Assets/Resources/Image/FullImageLogo/tetris-blitz-logo-kindf.png?cb=1412974297",
    "release_date": null,
    "additional_links": [

    ],
    "franchise": null,
    "platform": "pc",
    "genre": "horror"
  },
  {
    "name": "Tetris® Blitz for Android",
    "link": "http://www.ea.com/tetris-blitz-android",
    "thumbnail_link": "http://web-vassets.ea.com/Assets/Resources/Image/FeaturedGame/tetris-blitz-thumb-and.png?cb=1412974301",
    "logo_link": "http://web-vassets.ea.com/Assets/Resources/Image/FullImageLogo/tetris-blitz-logo-kindf.png?cb=1412974297",
    "release_date": null,
    "additional_links": [

    ],
    "franchise": null,
    "platform": "mobile",
    "genre": "action"
  },
  {
    "name": "MONOPOLY Slots for iPad and iPhone",
    "link": "http://www.ea.com/mosl-ios",
    "thumbnail_link": "http://web-vassets.ea.com/Assets/Resources/Image/FeaturedGame/monopoly-slots-thumb.png?cb=1412974174",
    "logo_link": "http://web-vassets.ea.com/Assets/Resources/Image/FullImageLogo/monopoly-slots-logo-ios.png?cb=1412974174",
    "release_date": null,
    "additional_links": [
      {
        "name": "View More Hasbro\n  Games",
        "link": "/hasbro"
      }
    ],
    "franchise": "/hasbro",
    "platform": "pc",
    "genre": "action"
  },
  {
    "name": "MONOPOLY Slots for Android",
    "link": "http://www.ea.com/mosl-and",
    "thumbnail_link": "http://web-vassets.ea.com/Assets/Resources/Image/FeaturedGame/monopoly-slots-thumb-and.png?cb=1412974174",
    "logo_link": "http://web-vassets.ea.com/Assets/Resources/Image/FullImageLogo/monopoly-slots-logo-and2.png?cb=1412974174",
    "release_date": null,
    "additional_links": [
      {
        "name": "View More Hasbro Games",
        "link": "/hasbro"
      }
    ],
    "franchise": "/hasbro",
    "platform": "pc",
    "genre": "action"
  },
  {
    "name": "Dungeon Keeper™ for iPad and iPhone",
    "link": "http://www.ea.com/dungeon-keeper-ios",
    "thumbnail_link": "http://web-vassets.ea.com/Assets/Resources/Image/FeaturedGame/dungeon-keeper-thumb-ios.png?cb=1412974188",
    "logo_link": "http://web-vassets.ea.com/Assets/Resources/Image/FullImageLogo/dungeon-keeper-logo-ios.png?cb=1412974188",
    "release_date": null,
    "additional_links": [

    ],
    "franchise": null,
    "platform": "mobile",
    "genre": "shooting"
  },
  {
    "name": "Dungeon Keeper™ for Kindle Fire",
    "link": "http://www.ea.com/dungeon-keeper-amz",
    "thumbnail_link": "http://web-vassets.ea.com/Assets/Resources/Image/FeaturedGame/dungeon-keeper-thumb-amz.png?cb=1412974118",
    "logo_link": "http://web-vassets.ea.com/Assets/Resources/Image/FullImageLogo/dungeon-keeper-logo-amz.png?cb=1412974118",
    "release_date": null,
    "additional_links": [

    ],
    "franchise": null,
    "platform": "mobile",
    "genre": "action"
  },
  {
    "name": "Dungeon Keeper™ for Android",
    "link": "http://www.ea.com/dungeon-keeper-and",
    "thumbnail_link": "http://web-vassets.ea.com/Assets/Resources/Image/FeaturedGame/dungeon-keeper-thumb-and.png?cb=1412974188",
    "logo_link": "http://web-vassets.ea.com/Assets/Resources/Image/FullImageLogo/dungeon-keeper-logo-and.png?cb=1412974188",
    "release_date": null,
    "additional_links": [

    ],
    "franchise": null,
    "platform": "mobile",
    "genre": "action"
  },
  {
    "name": "UFC",
    "link": "http://www.ea.com/ufc",
    "thumbnail_link": "http://web-vassets.ea.com/Assets/Resources/Image/FeaturedGame/EASPORTSUFC_298x1681.jpg?cb=1412974256",
    "logo_link": "http://web-vassets.ea.com/Assets/Resources/Image/FullImageLogo/EASPORTSUFC_gpd_logo.png?cb=1412974256",
    "release_date": null,
    "additional_links": [

    ],
    "franchise": null,
    "platform": "pc",
    "genre": "shooting"
  },
  {
    "name": "King of the Course Golf for Android",
    "link": "http://www.ea.com/kotc-and",
    "thumbnail_link": "http://web-vassets.ea.com/Assets/Resources/Image/FeaturedGame/king-of-the-course-thumb-and.png?cb=1408141630",
    "logo_link": "http://web-vassets.ea.com/Assets/Resources/Image/FullImageLogo/king-of-the-course-logo2-and.png?cb=1408141630",
    "release_date": null,
    "additional_links": [

    ],
    "franchise": null,
    "platform": "pc",
    "genre": "action"
  },
  {
    "name": "King of the Course Golf for iPad and iPhone",
    "link": "http://www.ea.com/kotc-ios",
    "thumbnail_link": "http://web-vassets.ea.com/Assets/Resources/Image/FeaturedGame/king-of-the-course-thumb.png?cb=1408141630",
    "logo_link": "http://web-vassets.ea.com/Assets/Resources/Image/FullImageLogo/king-of-the-course-logo2-ios.png?cb=1408141630",
    "release_date": null,
    "additional_links": [

    ],
    "franchise": null,
    "platform": "pc",
    "genre": "action"
  },
  {
    "name": "Titanfall",
    "link": "http://www.ea.com/titanfall",
    "thumbnail_link": "http://web-vassets.ea.com/Assets/Resources/Image/FeaturedGame/Titanfall_gdp_thumbnail_298x168.jpg?cb=1412974166",
    "logo_link": "http://web-vassets.ea.com/Assets/Resources/Image/FullImageLogo/Titanfall_gdp_logo.png?cb=1412974167",
    "release_date": null,
    "additional_links": [

    ],
    "franchise": null,
    "platform": "pc",
    "genre": "action"
  },
  {
    "name": "Plants vs. Zombies™ Garden Warfare",
    "link": "http://www.ea.com/garden-warfare",
    "thumbnail_link": "http://web-vassets.ea.com/Assets/Resources/Image/FeaturedGame/PvZ_GW_298x168.jpg?cb=1412974282",
    "logo_link": "http://web-vassets.ea.com/Assets/Resources/Image/FullImageLogo/new_hero_logo.png?cb=1412974257",
    "release_date": null,
    "additional_links": [

    ],
    "franchise": null,
    "platform": "pc",
    "genre": "action"
  },
  {
    "name": "Need For Speed Rivals",
    "link": "http://www.ea.com/rivals",
    "thumbnail_link": "http://web-vassets.ea.com/Assets/Resources/Image/FeaturedGame/NFSR_gdp_thumb_298x168.jpg?cb=1412974166",
    "logo_link": "http://web-vassets.ea.com/Assets/Resources/Image/FullImageLogo/NFSR_gpd_logo_v1.png?cb=1412974167",
    "release_date": null,
    "additional_links": [
      {
        "name": "View More Need for Speed Games",
        "link": "/nfs"
      }
    ],
    "franchise": "/nfs",
    "platform": "mobile",
    "genre": "horror"
  },
  {
    "name": "NBA LIVE 14",
    "link": "http://www.ea.com/nba-live",
    "thumbnail_link": "http://web-vassets.ea.com/Assets/Resources/Image/FeaturedGame/nba14.jpeg?cb=1412974200",
    "logo_link": "http://web-vassets.ea.com/Assets/Resources/Image/FullImageLogo/NBALIVE14-white_gpd_logo.png?cb=1412974256",
    "release_date": null,
    "additional_links": [

    ],
    "franchise": null,
    "platform": "pc",
    "genre": "shooting"
  },
  {
    "name": "Battlefield 4",
    "link": "http://www.ea.com/battlefield-4",
    "thumbnail_link": "http://web-vassets.ea.com/Assets/Resources/Image/FeaturedGame/BF4 298px × 168px.jpg?cb=1412974329",
    "logo_link": "http://web-vassets.ea.com/Assets/Resources/Image/FullImageLogo/BF4_gdp_logo.png?cb=1412974329",
    "release_date": null,
    "additional_links": [
      {
        "name": "View More Battlefield Games",
        "link": "/battlefield"
      }
    ],
    "franchise": "/battlefield",
    "platform": "xbox",
    "genre": "action"
  },
  {
    "name": "FIFA 14 by EA SPORTS™ for Android",
    "link": "http://www.ea.com/fifa-14-and",
    "thumbnail_link": "http://web-vassets.ea.com/Assets/Resources/Image/FeaturedGame/fifa14-thumb-and.png?cb=1412974197",
    "logo_link": "http://web-vassets.ea.com/Assets/Resources/Image/FullImageLogo/fifa14-logo-and.png?cb=1412974197",
    "release_date": null,
    "additional_links": [
      {
        "name": "View More FIFA Games",
        "link": "/fifa"
      }
    ],
    "franchise": "/fifa",
    "platform": "pc",
    "genre": "action"
  },
  {
    "name": "FIFA 14 by EA SPORTS™ for iPad and iPhone",
    "link": "http://www.ea.com/fifa-14-ios",
    "thumbnail_link": "http://web-vassets.ea.com/Assets/Resources/Image/FeaturedGame/fifa14-thumb-ios.png?cb=1412974197",
    "logo_link": "http://web-vassets.ea.com/Assets/Resources/Image/FullImageLogo/fifa14-logo-ios.png?cb=1412974197",
    "release_date": null,
    "additional_links": [
      {
        "name": "View More FIFA Games",
        "link": "/fifa"
      }
    ],
    "franchise": "/fifa",
    "platform": "mobile",
    "genre": "action"
  },
  {
    "name": "FIFA 14",
    "link": "http://www.ea.com/soccer",
    "thumbnail_link": "http://web-vassets.ea.com/Assets/Resources/Image/FeaturedGame/FIFA14_298x168.jpg?cb=1412974256",
    "logo_link": "http://web-vassets.ea.com/Assets/Resources/Image/FullImageLogo/FIFA14Gen4-white_gpd_logo.png?cb=1412974256",
    "release_date": null,
    "additional_links": [
      {
        "name": "View More FIFA Games",
        "link": "/fifa"
      }
    ],
    "franchise": "/fifa",
    "platform": "mobile",
    "genre": "action"
  },
  {
    "name": "NHL® 14",
    "link": "http://www.ea.com/nhl",
    "thumbnail_link": "http://web-vassets.ea.com/Assets/Resources/Image/FeaturedGame/nhl14.jpeg?cb=1412974200",
    "logo_link": "http://web-vassets.ea.com/Assets/Resources/Image/PromoImage/EASPORTSNHL14_gpd_logo.png?cb=1412974265",
    "release_date": null,
    "additional_links": [
      {
        "name": "View More NHL Games",
        "link": "/hockey"
      }
    ],
    "franchise": "/hockey",
    "platform": "mobile",
    "genre": "horror"
  },
  {
    "name": "Madden NFL 25",
    "link": "http://www.ea.com/madden-nfl",
    "thumbnail_link": "http://web-vassets.ea.com/Assets/Resources/Image/FeaturedGame/Madden25_298x168.jpg?cb=1412974265",
    "logo_link": "http://web-vassets.ea.com/Assets/Resources/Image/FullImageLogo/Madden25_gpd_logo.png?cb=1412974325",
    "release_date": null,
    "additional_links": [
      {
        "name": "View More Madden Games",
        "link": "/madden"
      }
    ],
    "franchise": "/madden",
    "platform": "pc",
    "genre": "shooting"
  },
  {
    "name": "MADDEN NFL 25 by EA SPORTS™ for iPad and iPhone",
    "link": "http://www.ea.com/madden-25-ios",
    "thumbnail_link": "http://web-vassets.ea.com/Assets/Resources/Image/FeaturedGame/madden25_thumb-ios.png?cb=1412974216",
    "logo_link": "http://web-vassets.ea.com/Assets/Resources/Image/FullImageLogo/madden25-logo-ios.png?cb=1412974216",
    "release_date": null,
    "additional_links": [
      {
        "name": "View\n  More Madden Games",
        "link": "/madden"
      }
    ],
    "franchise": "/madden",
    "platform": "mobile",
    "genre": "horror"
  },
  {
    "name": "NCAA Football 14",
    "link": "http://www.ea.com/ncaa-football-14",
    "thumbnail_link": "http://web-vassets.ea.com/Assets/Resources/Image/FeaturedGame/NCAAFootball14_298x168_v1.jpg?cb=1412974225",
    "logo_link": "http://web-vassets.ea.com/Assets/Resources/Image/FullImageLogo/NCAAFootball14_gpd_logo.png?cb=1412974288",
    "release_date": null,
    "additional_links": [

    ],
    "franchise": null,
    "platform": "pc",
    "genre": "shooting"
  },
  {
    "name": "The Sims 3 Island Paradise",
    "link": "http://www.ea.com/the-sims-3-island-paradise",
    "thumbnail_link": "http://web-vassets.ea.com/Assets/Resources/Image/FeaturedGame/TS3IP-298x168.jpg?cb=1412974353",
    "logo_link": "http://web-vassets.ea.com/Assets/Resources/Image/TS3IP-gpd-logo.png?cb=1412974353",
    "release_date": null,
    "additional_links": [
      {
        "name": "View More Sims Games",
        "link": "/sims"
      }
    ],
    "franchise": "/sims",
    "platform": "pc",
    "genre": "action"
  },
  {
    "name": "Fuse",
    "link": "http://www.ea.com/fuse",
    "thumbnail_link": "http://web-vassets.ea.com/Assets/Resources/Image/FeaturedGame/Fuse-298x168.jpg?cb=1412974457",
    "logo_link": "http://web-vassets.ea.com/Assets/Resources/Image/FullImageLogo/fuse_logo_final.png?cb=1412974403",
    "release_date": null,
    "additional_links": [

    ],
    "franchise": null,
    "platform": "mobile",
    "genre": "action"
  },
  {
    "name": "Plants vs. Zombies™ Adventures",
    "link": "http://www.ea.com/plants-vs-zombies-adventures",
    "thumbnail_link": "http://web-vassets.ea.com/Assets/Resources/Image/FeaturedGame/Thumb_Page_298x168_v1.jpg?cb=1427793005",
    "logo_link": "http://web-vassets.ea.com/Assets/Resources/Image/FullImageLogo/PvZ_GDP_logo.png?cb=1427793006",
    "release_date": null,
    "additional_links": [

    ],
    "franchise": null,
    "platform": "pc",
    "genre": "shooting"
  },
  {
    "name": "The Sims 3 Worlds Bundle",
    "link": "http://www.ea.com/the-sims-3-worlds-bundle",
    "thumbnail_link": "http://web-vassets.ea.com/Assets/Resources/Image/FeaturedGame/TS3_WorldsBundle_298x168.jpg?cb=1412974292",
    "logo_link": "http://web-vassets.ea.com/Assets/Resources/Image/FullImageLogo/TS3_WorldsBundle_GDP_logo.png?cb=1412974293",
    "release_date": null,
    "additional_links": [
      {
        "name": "View More Sims Games",
        "link": "/sims"
      }
    ],
    "franchise": "/sims",
    "platform": "pc",
    "genre": "horror"
  },
  {
    "name": "The Sims 3 Starter Pack",
    "link": "http://www.ea.com/the-sims-3-starter-pack",
    "thumbnail_link": "http://web-vassets.ea.com/Assets/Resources/Image/FeaturedGame/TS3StarterPack_298x168.jpg?cb=1412974293",
    "logo_link": "http://web-vassets.ea.com/Assets/Resources/Image/FullImageLogo/TS3StarterPack_gpd_logo.png?cb=1412974293",
    "release_date": null,
    "additional_links": [
      {
        "name": "View More Sims Games",
        "link": "/sims"
      }
    ],
    "franchise": "/sims",
    "platform": "mobile",
    "genre": "action"
  },
  {
    "name": "Bookworm Heroes",
    "link": "http://www.ea.com/bookworm-heroes-ios",
    "thumbnail_link": "http://web-vassets.ea.com/Assets/Resources/Image/FeaturedGame/bookworm_heroes_featured_298x168.jpg?cb=1412974314",
    "logo_link": "http://web-vassets.ea.com/Assets/Resources/Image/FullImageLogo/EA.com_Product_page_Assets_Logo_480x100.png?cb=1412974314",
    "release_date": null,
    "additional_links": [

    ],
    "franchise": null,
    "platform": "pc",
    "genre": "shooting"
  },
  {
    "name": "Tetris for iPhone",
    "link": "http://www.ea.com/tetris-iphone",
    "thumbnail_link": "http://web-vassets.ea.com/Assets/Richmedia/Image/FeaturedGame/tetris-2011-iphone-thumb.png?cb=1412974656",
    "logo_link": "http://web-vassets.ea.com/Assets/Richmedia/Image/FullImageLogo/tetris-2011-iphone-logo.png?cb=1412974656",
    "release_date": null,
    "additional_links": [

    ],
    "franchise": null,
    "platform": "xbox",
    "genre": "shooting"
  },
  {
    "name": "Tetris Mobile",
    "link": "http://www.ea.com/tetris-mobile",
    "thumbnail_link": "http://web-vassets.ea.com/Assets/Richmedia/Image/FeaturedGame/tetris-ipad-thumb.png?cb=1412974801",
    "logo_link": "http://web-vassets.ea.com/Assets/Richmedia/Image/FullImageLogo/tetris-ipad-logo.png?cb=1412974783",
    "release_date": null,
    "additional_links": [

    ],
    "franchise": null,
    "platform": "mobile",
    "genre": "action"
  },
  {
    "name": "Tetris for Android",
    "link": "http://www.ea.com/tetris-android",
    "thumbnail_link": "http://web-vassets.ea.com/Assets/Richmedia/Image/FeaturedGame/tetris-android-thumb.png?cb=1412974739",
    "logo_link": "http://web-vassets.ea.com/Assets/Richmedia/Image/FullImageLogo/tetris-android-logo.png?cb=1412974739",
    "release_date": null,
    "additional_links": [

    ],
    "franchise": null,
    "platform": "pc",
    "genre": "action"
  },
  {
    "name": "Tetris for iPad",
    "link": "http://www.ea.com/tetris-ipad",
    "thumbnail_link": "http://web-vassets.ea.com/Assets/Richmedia/Image/FeaturedGame/tetris-2011-ipad-thumb.png?cb=1412974555",
    "logo_link": "http://web-vassets.ea.com/Assets/Richmedia/Image/FullImageLogo/tetris-2011-ipad-logo.png?cb=1412974554",
    "release_date": null,
    "additional_links": [

    ],
    "franchise": null,
    "platform": "mobile",
    "genre": "shooting"
  },
  {
    "name": "Tetris for Windows Phone",
    "link": "http://www.ea.com/tetris-wp",
    "thumbnail_link": "http://web-vassets.ea.com/Assets/Richmedia/Image/FeaturedGame/tetris-wp7-thumb.png?cb=1412974734",
    "logo_link": "http://web-vassets.ea.com/Assets/Richmedia/Image/FullImageLogo/tetris-wp7-logo.png?cb=1412974734",
    "release_date": null,
    "additional_links": [

    ],
    "franchise": null,
    "platform": "pc",
    "genre": "shooting"
  },
  {
    "name": "Tetris for Kindle Fire",
    "link": "http://www.ea.com/tetris-kindle-fire",
    "thumbnail_link": "http://web-vassets.ea.com/Assets/Richmedia/Image/FeaturedGame/tetris-kindle-fire-thumb.png?cb=1412974599",
    "logo_link": "http://web-vassets.ea.com/Assets/Richmedia/Image/FullImageLogo/tetris-kindle-fire-logo.png?cb=1412974599",
    "release_date": null,
    "additional_links": [

    ],
    "franchise": null,
    "platform": "pc",
    "genre": "action"
  },
  {
    "name": "MONOPOLY Millionaire for Kindle Fire",
    "link": "http://www.ea.com/monopoly-millionaire-kf",
    "thumbnail_link": "http://web-vassets.ea.com/Assets/Resources/Image/FeaturedGame/monopoly-millionaire-kf-thumb.png?cb=1412974411",
    "logo_link": "http://web-vassets.ea.com/Assets/Resources/Image/FullImageLogo/monopoly-millionaire-kf-logo.png?cb=1412974411",
    "release_date": null,
    "additional_links": [
      {
        "name": "View More Hasbro Games",
        "link": "/hasbro"
      }
    ],
    "franchise": "/hasbro",
    "platform": "mobile",
    "genre": "action"
  },
  {
    "name": "MONOPOLY Millionaire for Android",
    "link": "http://www.ea.com/monopoly-millionaire-and",
    "thumbnail_link": "http://web-vassets.ea.com/Assets/Resources/Image/FeaturedGame/monopoly-millionaire-android-thumb.png?cb=1412974411",
    "logo_link": "http://web-vassets.ea.com/Assets/Resources/Image/FullImageLogo/monopoly-millionaire-android-logo.png?cb=1412974411",
    "release_date": null,
    "additional_links": [
      {
        "name": "View More Hasbro Games",
        "link": "/hasbro"
      }
    ],
    "franchise": "/hasbro",
    "platform": "pc",
    "genre": "shooting"
  },
  {
    "name": "Theme Park for iPad and iPhone ",
    "link": "http://www.ea.com/theme-park-ios",
    "thumbnail_link": "http://web-vassets.ea.com/Assets/Resources/Image/FeaturedGame/theme-park-thumb.png?cb=1412974513",
    "logo_link": "http://web-vassets.ea.com/Assets/Richmedia/Image/FullImageLogo/theme-park-logo.png?cb=1412974668",
    "release_date": null,
    "additional_links": [

    ],
    "franchise": null,
    "platform": "pc",
    "genre": "action"
  },
  {
    "name": "Theme Park for Android and Kindle Fire",
    "link": "http://www.ea.com/theme-park-and-kf",
    "thumbnail_link": "http://web-vassets.ea.com/Assets/Resources/Image/FeaturedGame/theme-park-and-thumb.png?cb=1412974425",
    "logo_link": "http://web-vassets.ea.com/Assets/Resources/Image/FullImageLogo/theme-park-logo.png?cb=1412974425",
    "release_date": null,
    "additional_links": [

    ],
    "franchise": null,
    "platform": "pc",
    "genre": "shooting"
  },
  {
    "name": "Dead Space for BlackBerry PlayBook",
    "link": "http://www.ea.com/dead-space-playbook",
    "thumbnail_link": "http://web-vassets.ea.com/Assets/Resources/Image/FeaturedGame/DS_Blackberry_298x168_new.jpg?cb=1412974377",
    "logo_link": "http://web-vassets.ea.com/Assets/Richmedia/Image/FullImageLogo/dead-space-playbook-logo.png?cb=1412974593",
    "release_date": null,
    "additional_links": [
      {
        "name": "View More Dead Space Games",
        "link": "/deadspace"
      }
    ],
    "franchise": "/deadspace",
    "platform": "mobile",
    "genre": "horror"
  }
]
